minx/__init__.py
minx/dialogue_processer.py
minx/estimator.py
minx/testprint.py
minx-0.0.2.dist-info/LICENSE
minx-0.0.2.dist-info/METADATA
minx-0.0.2.dist-info/WHEEL
minx-0.0.2.dist-info/top_level.txt
minx-0.0.2.dist-info/RECORD
