Metadata-Version: 2.1
Name: minx
Version: 0.0.2
Summary: It's a test
Author-email: Minx <minxinm@foxmail.com>
License: MIT License
Classifier: Programming Language :: Python :: 3
Classifier: License :: OSI Approved :: MIT License
Classifier: Operating System :: OS Independent
Requires-Python: >=3.7
License-File: LICENSE
